{
 "captured_at": "2026-07-24T20:08:56Z",
 "matches": [
  {
   "event_id": 35861581,
   "p1": "Maciej Kolek",
   "p2": "Artur Daniel",
   "p1_norm": "maciej kolek",
   "p2_norm": "artur daniel",
   "open_date": "2026-07-24T20:05:00.000Z",
   "line": 76.5,
   "over_odds": -110,
   "under_odds": -125
  },
  {
   "event_id": 35861597,
   "p1": "Michal Natkaniec",
   "p2": "Michal Guzik",
   "p1_norm": "michal natkaniec",
   "p2_norm": "michal guzik",
   "open_date": "2026-07-24T20:20:00.000Z",
   "line": 74.5,
   "over_odds": -112,
   "under_odds": -118
  },
  {
   "event_id": 35861598,
   "p1": "Roman Wiza",
   "p2": "Piotr Gumulinski",
   "p1_norm": "roman wiza",
   "p2_norm": "piotr gumulinski",
   "open_date": "2026-07-24T20:20:00.000Z",
   "line": 76.5,
   "over_odds": -112,
   "under_odds": -118
  },
  {
   "event_id": 35861615,
   "p1": "Michal Skorski",
   "p2": "Mateusz Trela",
   "p1_norm": "michal skorski",
   "p2_norm": "mateusz trela",
   "open_date": "2026-07-24T20:30:00.000Z",
   "line": 81.5,
   "over_odds": -118,
   "under_odds": -112
  },
  {
   "event_id": 35861616,
   "p1": "Jakub Jesiek",
   "p2": "Wojciech Wojtaszczyk",
   "p1_norm": "jakub jesiek",
   "p2_norm": "wojciech wojtaszczyk",
   "open_date": "2026-07-24T20:30:00.000Z",
   "line": 74.5,
   "over_odds": -118,
   "under_odds": -112
  },
  {
   "event_id": 35861617,
   "p1": "Kamil Kostyk",
   "p2": "Michal Olbrycht",
   "p1_norm": "kamil kostyk",
   "p2_norm": "michal olbrycht",
   "open_date": "2026-07-24T20:30:00.000Z",
   "line": 78.5,
   "over_odds": -112,
   "under_odds": -118
  }
 ]
}