{
 "captured_at": "2026-07-19T20:39:41Z",
 "matches": [
  {
   "event_id": 35843545,
   "p1": "Adam Linek",
   "p2": "Gracjan Kesik",
   "p1_norm": "adam linek",
   "p2_norm": "gracjan kesik",
   "open_date": "2026-07-19T20:30:00.000Z",
   "line": 70.5,
   "over_odds": -110,
   "under_odds": -125
  },
  {
   "event_id": 35843546,
   "p1": "Filip Mlynarski",
   "p2": "Jakub Kuzmicz",
   "p1_norm": "filip mlynarski",
   "p2_norm": "jakub kuzmicz",
   "open_date": "2026-07-19T20:30:00.000Z",
   "line": 56.5,
   "over_odds": -105,
   "under_odds": -130
  },
  {
   "event_id": 35843547,
   "p1": "Andriej Fomin",
   "p2": "Zbigniew Nocun",
   "p1_norm": "andriej fomin",
   "p2_norm": "zbigniew nocun",
   "open_date": "2026-07-19T20:30:00.000Z",
   "line": 70.5,
   "over_odds": -115,
   "under_odds": -120
  },
  {
   "event_id": 35843552,
   "p1": "Sebastian Juzek",
   "p2": "Jaroslaw Badura",
   "p1_norm": "sebastian juzek",
   "p2_norm": "jaroslaw badura",
   "open_date": "2026-07-19T20:45:00.000Z",
   "line": 77.5,
   "over_odds": -110,
   "under_odds": -120
  },
  {
   "event_id": 35843553,
   "p1": "Rafal Adach",
   "p2": "Wojciech Urban",
   "p1_norm": "rafal adach",
   "p2_norm": "wojciech urban",
   "open_date": "2026-07-19T20:45:00.000Z",
   "line": 77.5,
   "over_odds": -118,
   "under_odds": -112
  },
  {
   "event_id": 35843591,
   "p1": "Adam Linek",
   "p2": "Aleksander Lilien",
   "p1_norm": "adam linek",
   "p2_norm": "aleksander lilien",
   "open_date": "2026-07-19T21:00:00.000Z",
   "line": 76.5,
   "over_odds": -112,
   "under_odds": -118
  },
  {
   "event_id": 35843592,
   "p1": "Filip Mlynarski",
   "p2": "Mateusz Rutkowski",
   "p1_norm": "filip mlynarski",
   "p2_norm": "mateusz rutkowski",
   "open_date": "2026-07-19T21:00:00.000Z",
   "line": 75.5,
   "over_odds": -116,
   "under_odds": -116
  },
  {
   "event_id": 35843593,
   "p1": "Mariusz Baron",
   "p2": "Grzegorz Marud",
   "p1_norm": "mariusz baron",
   "p2_norm": "grzegorz marud",
   "open_date": "2026-07-19T21:05:00.000Z",
   "line": 77.5,
   "over_odds": -116,
   "under_odds": -116
  }
 ]
}