{
 "captured_at": "2026-07-23T01:31:18Z",
 "matches": [
  {
   "event_id": 35854694,
   "p1": "Pawel Chojnacki",
   "p2": "Kacper Kwiatkowski",
   "p1_norm": "pawel chojnacki",
   "p2_norm": "kacper kwiatkowski",
   "open_date": "2026-07-23T01:25:00.000Z",
   "line": 87.5,
   "over_odds": -115,
   "under_odds": -115
  },
  {
   "event_id": 35854695,
   "p1": "Adrian Fabis",
   "p2": "Kuba Golaszewski",
   "p1_norm": "adrian fabis",
   "p2_norm": "kuba golaszewski",
   "open_date": "2026-07-23T01:25:00.000Z",
   "line": 73.5,
   "over_odds": -115,
   "under_odds": -120
  }
 ]
}