{
 "captured_at": "2026-07-24T06:21:41Z",
 "matches": [
  {
   "event_id": 35858655,
   "p1": "Blazej Warpas",
   "p2": "Bartosz Sulkowski",
   "p1_norm": "blazej warpas",
   "p2_norm": "bartosz sulkowski",
   "open_date": "2026-07-24T06:05:00.000Z",
   "line": 91.5,
   "over_odds": -130,
   "under_odds": -105
  },
  {
   "event_id": 35858656,
   "p1": "Marcin Jadczyk",
   "p2": "Adrian Spychala",
   "p1_norm": "marcin jadczyk",
   "p2_norm": "adrian spychala",
   "open_date": "2026-07-24T06:05:00.000Z",
   "line": 86.5,
   "over_odds": -105,
   "under_odds": -135
  },
  {
   "event_id": 35858657,
   "p1": "Robert Kostepski",
   "p2": "Sebastian Szostok",
   "p1_norm": "robert kostepski",
   "p2_norm": "sebastian szostok",
   "open_date": "2026-07-24T06:05:00.000Z",
   "line": 74.5,
   "over_odds": 100,
   "under_odds": -135
  },
  {
   "event_id": 35858676,
   "p1": "Grzegorz Jurowicz",
   "p2": "Jerzy Pelka",
   "p1_norm": "grzegorz jurowicz",
   "p2_norm": "jerzy pelka",
   "open_date": "2026-07-24T06:20:00.000Z",
   "line": 78.5,
   "over_odds": -115,
   "under_odds": -120
  },
  {
   "event_id": 35858680,
   "p1": "Lukasz Oracz",
   "p2": "Marek Tkocz",
   "p1_norm": "lukasz oracz",
   "p2_norm": "marek tkocz",
   "open_date": "2026-07-24T06:25:00.000Z",
   "line": 74.5,
   "over_odds": -118,
   "under_odds": -112
  },
  {
   "event_id": 35858681,
   "p1": "Stapor Rafal",
   "p2": "Dawid Kosmal",
   "p1_norm": "stapor rafal",
   "p2_norm": "dawid kosmal",
   "open_date": "2026-07-24T06:25:00.000Z",
   "line": 76.5,
   "over_odds": -118,
   "under_odds": -112
  },
  {
   "event_id": 35858689,
   "p1": "Krzysztof Kotyl",
   "p2": "Arkadiusz Mugowski",
   "p1_norm": "krzysztof kotyl",
   "p2_norm": "arkadiusz mugowski",
   "open_date": "2026-07-24T06:30:00.000Z",
   "line": 80.5,
   "over_odds": -112,
   "under_odds": -118
  },
  {
   "event_id": 35858690,
   "p1": "Piotr Cyrnek",
   "p2": "Martin Olejnik",
   "p1_norm": "piotr cyrnek",
   "p2_norm": "martin olejnik",
   "open_date": "2026-07-24T06:30:00.000Z",
   "line": 78.5,
   "over_odds": -118,
   "under_odds": -112
  },
  {
   "event_id": 35858691,
   "p1": "Pawel Kurek",
   "p2": "Jakub Kaczmarek",
   "p1_norm": "pawel kurek",
   "p2_norm": "jakub kaczmarek",
   "open_date": "2026-07-24T06:30:00.000Z",
   "line": 75.5,
   "over_odds": -118,
   "under_odds": -112
  },
  {
   "event_id": 35858712,
   "p1": "Marian Lebek",
   "p2": "Michal Paszkiewicz",
   "p1_norm": "marian lebek",
   "p2_norm": "michal paszkiewicz",
   "open_date": "2026-07-24T06:45:00.000Z",
   "line": 77.5,
   "over_odds": -112,
   "under_odds": -118
  },
  {
   "event_id": 35858713,
   "p1": "Grzegorz Wichowski",
   "p2": "Rafal Niemiec",
   "p1_norm": "grzegorz wichowski",
   "p2_norm": "rafal niemiec",
   "open_date": "2026-07-24T06:45:00.000Z",
   "line": 78.5,
   "over_odds": -118,
   "under_odds": -112
  }
 ]
}