{
 "captured_at": "2026-07-16T22:21:23Z",
 "matches": [
  {
   "event_id": 35832460,
   "p1": "Patryk Jendrzejewski",
   "p2": "Tomasz Filbrandt",
   "p1_norm": "patryk jendrzejewski",
   "p2_norm": "tomasz filbrandt",
   "open_date": "2026-07-16T22:05:00.000Z",
   "line": 90.5,
   "over_odds": null,
   "under_odds": null
  },
  {
   "event_id": 35832463,
   "p1": "Mikolaj Lukaszewski",
   "p2": "Jaroslaw Rolak",
   "p1_norm": "mikolaj lukaszewski",
   "p2_norm": "jaroslaw rolak",
   "open_date": "2026-07-16T22:10:00.000Z",
   "line": 80.5,
   "over_odds": -120,
   "under_odds": -115
  },
  {
   "event_id": 35832497,
   "p1": "Michal Guzik",
   "p2": "Mateusz Karpiuk",
   "p1_norm": "michal guzik",
   "p2_norm": "mateusz karpiuk",
   "open_date": "2026-07-16T22:10:00.000Z",
   "line": 86.5,
   "over_odds": -120,
   "under_odds": -115
  },
  {
   "event_id": 35832471,
   "p1": "Jakub Nowak",
   "p2": "Kacper Adamus",
   "p1_norm": "jakub nowak",
   "p2_norm": "kacper adamus",
   "open_date": "2026-07-16T22:25:00.000Z",
   "line": 80.5,
   "over_odds": -116,
   "under_odds": -116
  },
  {
   "event_id": 35832484,
   "p1": "Konrad Staszczyk",
   "p2": "Tomasz Filbrandt",
   "p1_norm": "konrad staszczyk",
   "p2_norm": "tomasz filbrandt",
   "open_date": "2026-07-16T22:30:00.000Z",
   "line": 77.5,
   "over_odds": -118,
   "under_odds": -112
  },
  {
   "event_id": 35832488,
   "p1": "Kazimierz Rybak",
   "p2": "Henryk Tkaczyk",
   "p1_norm": "kazimierz rybak",
   "p2_norm": "henryk tkaczyk",
   "open_date": "2026-07-16T22:35:00.000Z",
   "line": 67.5,
   "over_odds": -110,
   "under_odds": -120
  },
  {
   "event_id": 35832489,
   "p1": "Michal Skorski",
   "p2": "Jaroslaw Rolak",
   "p1_norm": "michal skorski",
   "p2_norm": "jaroslaw rolak",
   "open_date": "2026-07-16T22:35:00.000Z",
   "line": 78.5,
   "over_odds": -112,
   "under_odds": -118
  },
  {
   "event_id": 35832494,
   "p1": "Adam Staniczek",
   "p2": "Dawid Pyrek",
   "p1_norm": "adam staniczek",
   "p2_norm": "dawid pyrek",
   "open_date": "2026-07-16T22:40:00.000Z",
   "line": 73.5,
   "over_odds": -118,
   "under_odds": -112
  }
 ]
}