{"fetched": "2026-07-21T16:46:10.257655-04:00", "stamp": "2026-07-21_04_45PM", "mark": "2026-07-21T16:45:00-04:00", "rows": [{"game_date": "2026-07-22", "matchup": "CHI@NYL", "team": "CHI", "player": "DiJonai Carrington", "status": "Out", "reason": "Injury/Illness - Left Foot; Left Foot"}, {"game_date": "2026-07-22", "matchup": "CHI@NYL", "team": "CHI", "player": "Skylar Diggins", "status": "Out", "reason": "Injury/Illness - Right Knee; Right Knee"}, {"game_date": "2026-07-22", "matchup": "CON@IND", "team": "CON", "player": "Aaliyah Edwards", "status": "Out", "reason": "Injury/Illness - Right Knee; -"}, {"game_date": "2026-07-22", "matchup": "CON@IND", "team": "CON", "player": "Brittney Griner", "status": "Questionable", "reason": "Injury/Illness - Left Knee; -"}, {"game_date": "2026-07-22", "matchup": "CON@IND", "team": "CON", "player": "Saniya Rivers", "status": "Questionable", "reason": "Injury/Illness - Left Ankle; /Foot"}], "submitted": {"2026-07-22|MIN": false, "2026-07-22|SEA": false, "2026-07-22|PHX": false, "2026-07-22|LA": false, "2026-07-22|CHI": true, "2026-07-22|NY": false, "2026-07-22|LV": false, "2026-07-22|CON": true, "2026-07-22|IND": false, "2026-07-22|DAL": false, "2026-07-22|POR": false}}